funsql/__init__.py
funsql/clausedefs.py
funsql/clauses.py
funsql/common.py
funsql/nodedefs.py
funsql/nodes.py
funsql/prettier.py
funsql/render.py
funsql/sqlcontext.py
funsql/compiler/__init__.py
funsql/compiler/annotate.py
funsql/compiler/link.py
funsql/compiler/resolve.py
funsql/compiler/serialize.py
funsql/compiler/translate.py
funsql/compiler/types.py
funsql/prettyprint/__init__.py
funsql/prettyprint/printer.py
funsql/tools/__init__.py
funsql/tools/dialects.py
funsql/tools/reflect.py
funsql/tools/utilities.py
funsql_python-0.2.0.dist-info/LICENSE
funsql_python-0.2.0.dist-info/METADATA
funsql_python-0.2.0.dist-info/WHEEL
funsql_python-0.2.0.dist-info/top_level.txt
funsql_python-0.2.0.dist-info/RECORD
