Metadata-Version: 2.1
Name: funsql-python
Version: 0.2.0
Summary: library to write compositional sql
Home-page: https://github.com/ananis25/funsql-python
Author: Ishan Anand
Classifier: Programming Language :: Python :: 3 :: Only
Classifier: License :: OSI Approved :: MIT License
Classifier: Operating System :: OS Independent
Requires-Python: >=3.7
License-File: LICENSE
Provides-Extra: dev
Requires-Dist: pytest (>=7.0) ; extra == 'dev'
Requires-Dist: nbconvert (>=6.4) ; extra == 'dev'
Requires-Dist: nbstripout (>=0.5) ; extra == 'dev'
Requires-Dist: jupyterlab (>=3.0) ; extra == 'dev'
